nn_interface/__init__.py
nn_interface/data.py
nn_interface/io.py
nn_interface/nn.py
nn_interface/pipeline.py
nn_interface/processor.py
nn_interface/type.py
nn_interface/utils.py
nn_interface-1.0.2.dist-info/METADATA
nn_interface-1.0.2.dist-info/WHEEL
nn_interface-1.0.2.dist-info/top_level.txt
nn_interface-1.0.2.dist-info/RECORD
